{
  "name": "Product",
  "base": "PersistedModel",
  "idInjection": true,
  "options": {
    "validateUpsert": true
  },
  "properties": {
    "name": {
      "type": "string",
      "required": true
    },
    "description": {
      "type": "string"
    },
    "price": {
      "type": "number",
      "required": true,
      "default": 0
    },
    "restaurantId": {
      "type": "number",
      "required": true
    },
    "created": {
      "type": "date",
      "defaultFn": "now"
    },
    "modified": {
      "type": "date",
      "defaultFn": "now"
    }
  },
  "validations": [],
  "relations": {
    "owner": {
      "type": "belongsTo",
      "model": "Restaurant",
      "foreignKey": "restaurantId"
    },
    "pictures": {
      "type": "hasMany",
      "model": "Picture",
      "polymorphic": "imageable"
    }
  },
  "acls": [],
  "methods": {}
}
